RikPy/.gitignore
RikPy/__init__.py
RikPy/commonairtable.py
RikPy/commonfunctions.py
RikPy/commongoogle.py
RikPy/commonheroku.py
RikPy/commonleonardo.py
RikPy/commonlogging.py
RikPy/commonopenai.py
RikPy/commons3.py
RikPy/commonshopify.py
RikPy/customresponse.py
rikpy-1.0.0.dist-info/METADATA
rikpy-1.0.0.dist-info/WHEEL
rikpy-1.0.0.dist-info/licenses/LICENSE
rikpy-1.0.0.dist-info/RECORD
