Metadata-Version: 2.4
Name: rikpy
Version: 1.0.0
Summary: Python package by Rik
Project-URL: Homepage, https://github.com/rfp-byte/RikPy
Author-email: Rik <richard@blipi.me>
License-File: LICENSE
Classifier: License :: OSI Approved :: MIT License
Classifier: Operating System :: OS Independent
Classifier: Programming Language :: Python :: 3
Requires-Python: >=3.7
